{
  "schemaVersion": 1,
  "fetchedAt": 1782389219395,
  "contentHash": "7d800861344d",
  "breaking": [
    {
      "title": "Venezuela earthquake LIVE: At least 164 dead, 971 injured in quakes, says Interim President Delcy Rodríguez",
      "summary": "World leaders offer solidarity and aid as country reels from quakes",
      "source": "The Hindu",
      "sourceGroup": "the_hindu",
      "url": "https://www.thehindu.com/news/international/venezuela-earthquakes-live-updates-terremoto-caracas-magnitude-7-tsunami-alert-damages-death-toll-live-updates-june-25-2026/article71144983.ece",
      "publishedAt": 1782389067000,
      "category": "topStories",
      "region": "in",
      "language": "en",
      "id": "7227a01bd0a2f450",
      "suppressionReason": null,
      "isBreaking": true,
      "breakingScore": 5.496,
      "breakingReasons": [
        "severity_lexicon"
      ],
      "sourceCount": 2,
      "allSources": [
        "ndtv",
        "the_hindu"
      ],
      "firstSeen": 1782383281000
    },
    {
      "title": "Businessman found dead in actor Krishi Thapanda’s residence in Bengaluru",
      "summary": "He is said to have sent messages to the actor indicating that he intended to end his life",
      "source": "The Hindu National",
      "sourceGroup": "the_hindu",
      "url": "https://www.thehindu.com/news/cities/bangalore/businessman-vaishak-found-dead-in-actor-krishi-thapandas-residence-in-bengaluru/article71145571.ece",
      "publishedAt": 1782388249000,
      "category": "india",
      "region": "in",
      "language": "en",
      "id": "3f61915c49b1044d",
      "suppressionReason": null,
      "isBreaking": true,
      "breakingScore": 4.478,
      "breakingReasons": [
        "multi_source_velocity",
        "severity_lexicon"
      ],
      "sourceCount": 2,
      "allSources": [
        "ndtv",
        "the_hindu"
      ],
      "firstSeen": 1782383690000
    },
    {
      "title": "What we know so far",
      "summary": "The two quakes have killed at least 164 people and injured nearly 1,000, with more feared trapped under rubble.",
      "source": "BBC",
      "sourceGroup": "bbc",
      "url": "https://www.bbc.co.uk/news/articles/c4gyjgreg1ro?at_medium=RSS&at_campaign=rss",
      "publishedAt": 1782388870000,
      "category": "world",
      "region": "in",
      "language": "en",
      "id": "6c89c874421c61d7",
      "suppressionReason": null,
      "isBreaking": true,
      "breakingScore": 3.992,
      "breakingReasons": [
        "severity_lexicon"
      ],
      "sourceCount": 1,
      "allSources": [
        "bbc"
      ],
      "firstSeen": 1782388870000
    },
    {
      "title": "Congo’s Ebola outbreak has most cases in first month of any African outbreak, WHO says",
      "summary": "The Bundibugyo outbreak in the Democratic Republic ‌of Congo that has infected over 1,000 people and killed 267 ‌was detected late and experts say ‌the ⁠virus had already been circulating ⁠for months before it was officially declared on May 15",
      "source": "The Hindu International",
      "sourceGroup": "the_hindu",
      "url": "https://www.thehindu.com/sci-tech/health/congos-ebola-outbreak-has-most-cases-in-first-month-of-any-african-outbreak-who-says/article71138029.ece",
      "publishedAt": 1782387431000,
      "category": "world",
      "region": "in",
      "language": "en",
      "id": "eae76a31ae86d103",
      "suppressionReason": null,
      "isBreaking": true,
      "breakingScore": 3.959,
      "breakingReasons": [
        "severity_lexicon"
      ],
      "sourceCount": 1,
      "allSources": [
        "the_hindu"
      ],
      "firstSeen": 1782387431000
    },
    {
      "title": "West Asia war LIVE: Israel must withdraw entirely from Lebanon, Iran's guards say",
      "summary": "On deal with Iran, U.S. Secretary of State Marco Rubio said open for peace without undermining security of U.S., its allies; he is in Bahrain for a Gulf Cooperation Council meeting",
      "source": "The Hindu",
      "sourceGroup": "the_hindu",
      "url": "https://www.thehindu.com/news/international/west-asia-war-iran-usa-israel-conflict-washington-tehran-peace-deal-donald-trump-strait-of-hormuz-live-updates-june-25-2026/article71144582.ece",
      "publishedAt": 1782389079000,
      "category": "topStories",
      "region": "in",
      "language": "en",
      "id": "e7d8bb0872783258",
      "suppressionReason": null,
      "isBreaking": true,
      "breakingScore": 2.497,
      "breakingReasons": [
        "severity_lexicon"
      ],
      "sourceCount": 1,
      "allSources": [
        "the_hindu"
      ],
      "firstSeen": 1782388670000
    },
    {
      "title": "Trump says it may never be known who was at fault for strike on girls' school in Iran",
      "summary": "",
      "source": "The Hindu",
      "sourceGroup": "the_hindu",
      "url": "https://www.thehindu.com/news/international/trump-says-it-may-never-be-known-who-was-at-fault-for-strike-on-girls-school-in-iran/article71143766.ece",
      "publishedAt": 1782388628000,
      "category": "topStories",
      "region": "in",
      "language": "en",
      "id": "e37a7cfe23d004d2",
      "suppressionReason": null,
      "isBreaking": true,
      "breakingScore": 2.486,
      "breakingReasons": [
        "severity_lexicon"
      ],
      "sourceCount": 1,
      "allSources": [
        "the_hindu"
      ],
      "firstSeen": 1782388628000
    },
    {
      "title": "Scrap NEET, return medical admissions to States: PDSO protest in Visakhapatnam",
      "summary": "The students’ body said NEET, JEE and CUET were putting aspirants under severe stress, and sought the resignation of Union Education Minister Dharmendra Pradhan",
      "source": "The Hindu",
      "sourceGroup": "the_hindu",
      "url": "https://www.thehindu.com/news/national/andhra-pradesh/scrap-neet-return-medical-admissions-to-states-pdso-protest-in-visakhapatnam/article71145157.ece",
      "publishedAt": 1782388494000,
      "category": "topStories",
      "region": "in",
      "language": "en",
      "id": "f08603acc2c349a4",
      "suppressionReason": null,
      "isBreaking": true,
      "breakingScore": 2.483,
      "breakingReasons": [
        "severity_lexicon"
      ],
      "sourceCount": 1,
      "allSources": [
        "the_hindu"
      ],
      "firstSeen": 1782388494000
    },
    {
      "title": "Civil Aviation Ministry, DIAL launch Air Suvidha 2.0 portal for Ebola health screening at points of entry in India",
      "summary": "The launch follows the World Health Organisation’s declaration of Ebola/Bundibugyo virus disease outbreak in the Democratic Republic of the Congo and Uganda as a Public Health Emergency of International Concern (PHEIC) last month",
      "source": "The Hindu National",
      "sourceGroup": "the_hindu",
      "url": "https://www.thehindu.com/news/national/civil-aviation-ministry-dial-launch-portal-for-ebola-health-screening-at-points-of-entry/article71145810.ece",
      "publishedAt": 1782387970000,
      "category": "india",
      "region": "in",
      "language": "en",
      "id": "85996dd4b5fcb35e",
      "suppressionReason": null,
      "isBreaking": true,
      "breakingScore": 2.471,
      "breakingReasons": [
        "severity_lexicon"
      ],
      "sourceCount": 1,
      "allSources": [
        "the_hindu"
      ],
      "firstSeen": 1782387970000
    }
  ]
}