{
  "checks": [
    {
      "ageHours": 0.01,
      "ageMs": 20973,
      "contentHash": "88d40dc14c7d6371",
      "errors": [],
      "fetchedAt": 1782044704841,
      "name": "insight",
      "path": "public/newsdata/insight_latest.json",
      "status": "PASS",
      "storyCount": 498,
      "warnings": []
    },
    {
      "ageHours": 0.0,
      "ageMs": 11390,
      "contentHash": "23681587ebb5",
      "errors": [],
      "fetchedAt": 1782044714424,
      "name": "sections",
      "path": "public/newsdata/sections_latest.json",
      "status": "PASS",
      "storyCount": 279,
      "warnings": []
    }
  ],
  "errors": [],
  "generatedAt": 1782044725814,
  "schemaVersion": 1,
  "status": "PASS",
  "thresholds": {
    "maxAgeHours": 6.0,
    "maxFutureSkewMinutes": 10.0
  },
  "warnings": []
}