{
  "checks": [
    {
      "ageHours": 0.01,
      "ageMs": 24875,
      "contentHash": "160f4870ff4c6584",
      "errors": [],
      "fetchedAt": 1781913986765,
      "name": "insight",
      "path": "public/newsdata/insight_latest.json",
      "status": "PASS",
      "storyCount": 631,
      "warnings": []
    },
    {
      "ageHours": 0.0,
      "ageMs": 12779,
      "contentHash": "dcabbe63ed61",
      "errors": [],
      "fetchedAt": 1781913998861,
      "name": "sections",
      "path": "public/newsdata/sections_latest.json",
      "status": "PASS",
      "storyCount": 287,
      "warnings": []
    }
  ],
  "errors": [],
  "generatedAt": 1781914011640,
  "schemaVersion": 1,
  "status": "PASS",
  "thresholds": {
    "maxAgeHours": 6.0,
    "maxFutureSkewMinutes": 10.0
  },
  "warnings": []
}