{
  "schemaVersion": "2.0.0",
  "generatedAt": "2026-06-02T03:44:49.393464Z",
  "currencies": [
    {
      "name": "EUR/INR",
      "pair": "EURINR",
      "symbol": "EURINR=X",
      "value": "₹110.6568",
      "rate": 110.65679931640625,
      "change": "-0.0502",
      "changePercent": "-0.05",
      "direction": "down",
      "source": "yahoo-yfinance",
      "mode": "fallback-intraday",
      "asOf": "2026-06-02T03:43:07.636403Z"
    },
    {
      "name": "JPY/INR",
      "pair": "JPYINR",
      "symbol": "JPYINR=X",
      "value": "₹0.5955",
      "rate": 0.59552001953125,
      "change": "-0.0014",
      "changePercent": "-0.23",
      "direction": "down",
      "source": "yahoo-yfinance",
      "mode": "fallback-intraday",
      "asOf": "2026-06-02T03:43:07.683391Z"
    },
    {
      "name": "GBP/INR",
      "pair": "GBPINR",
      "symbol": "GBPINR=X",
      "value": "₹127.9963",
      "rate": 127.99629974365234,
      "change": "0.6960",
      "changePercent": "0.55",
      "direction": "up",
      "source": "yahoo-yfinance",
      "mode": "fallback-intraday",
      "asOf": "2026-06-02T03:43:07.712821Z"
    },
    {
      "name": "OMR/INR",
      "pair": "OMRINR",
      "symbol": "OMRINR=X",
      "value": "₹246.3400",
      "rate": 246.33999633789062,
      "change": "0.0000",
      "changePercent": "0.00",
      "direction": "up",
      "source": "yahoo-yfinance",
      "mode": "fallback-intraday",
      "asOf": "2026-06-02T03:43:07.719844Z"
    },
    {
      "name": "USD/INR",
      "pair": "USDINR",
      "symbol": "USDINR=X",
      "value": "₹95.1030",
      "rate": 95.10299682617188,
      "change": "0.1000",
      "changePercent": "0.11",
      "direction": "up",
      "source": "yahoo-yfinance",
      "mode": "fallback-intraday",
      "asOf": "2026-06-02T03:43:07.766694Z"
    }
  ],
  "sourceHealth": {
    "status": "ok",
    "freshnessMs": 0,
    "winner": "yahoo_yfinance",
    "providersTried": [
      {
        "provider": "rbi_reference",
        "status": "failed",
        "latencyMs": null,
        "count": 0,
        "message": "RBI reference scrape failed: unknown"
      },
      {
        "provider": "yahoo_yfinance",
        "status": "ok",
        "latencyMs": null,
        "count": 5,
        "message": "5 FX pairs fetched from Yahoo fallback"
      }
    ],
    "notes": []
  }
}
